dataclass_map_and_log/__init__.py
dataclass_map_and_log/mapper.py
dataclass_map_and_log-0.1.6.dist-info/METADATA
dataclass_map_and_log-0.1.6.dist-info/WHEEL
dataclass_map_and_log-0.1.6.dist-info/licenses/LICENSE
dataclass_map_and_log-0.1.6.dist-info/RECORD
