Metadata-Version: 2.4
Name: dataclass_map_and_log
Version: 0.1.6
Summary: Map a dict to a dataclass and log differences
Author-email: José Ignacio Amelivia Santiago <hello@namelivia.com>
License-File: LICENSE
Classifier: Development Status :: 5 - Production/Stable
Classifier: Intended Audience :: Developers
Classifier: License :: OSI Approved :: MIT License
Classifier: Programming Language :: Python :: 3.8
Classifier: Programming Language :: Python :: 3.9
Classifier: Programming Language :: Python :: 3.10
Classifier: Programming Language :: Python :: 3.11
Classifier: Topic :: Software Development :: Build Tools
Requires-Python: <3.11,>=3.8
